{
    "title": "BSC Contabilidade",
    "phone": "01236327888",
    "category": "Assessoria cont\u00e1bil",
    "address": " R. Padre Fischer, 488 - Parque Sao Luis, Taubat\u00e9 - SP, 12061-600 ",
    "website": "http://bsccontabilidade.com.br/",
    "reviews": 4,
    "rating": "5,0",
    "link": "https://www.google.com/maps/place/BSC+Contabilidade/data=!4m7!3m6!1s0x94ccf9ba90195d53:0xbfd905dbc245b216!8m2!3d-23.0074799!4d-45.5528449!16s%2Fg%2F11c3k2v1s3!19sChIJU10ZkLr5zJQRFrJFwtsF2b8?authuser=0&hl=pt-BR&rclk=1"
}