{
    "title": "Escola Place Kids",
    "phone": "01150617608",
    "category": "Escola",
    "address": " R. Visc. de Piraj\u00e1, 303 - Vila Dom Pedro I, S\u00e3o Paulo - SP, 04277-020 ",
    "website": "http://www.escolaplace.com/",
    "reviews": 21,
    "rating": "4,2",
    "link": "https://www.google.com/maps/place/Escola+Place+Kids/data=!4m7!3m6!1s0x94ce5bd6e984d2cd:0xfa555fb604720a69!8m2!3d-23.6008671!4d-46.6127255!16s%2Fg%2F11fntd7gy_!19sChIJzdKE6dZbzpQRaQpyBLZfVfo?authuser=0&hl=pt-BR&rclk=1"
}