{
    "title": "Escola Estadual Lasar Segall",
    "phone": "01155494833",
    "category": "Escola p\u00fablica",
    "address": " R. Dr. Tirso Martins, 211 - Vila Mariana, S\u00e3o Paulo - SP, 04120-050 ",
    "website": "http://www.educacao.sp.gov.br/cgrh/escolas/lasar-segall",
    "reviews": 77,
    "rating": "4,5",
    "link": "https://www.google.com/maps/place/Escola+Estadual+Lasar+Segall/data=!4m7!3m6!1s0x94ce5a2d821518bf:0x816b691ae22d4758!8m2!3d-23.5953992!4d-46.634169!16s%2Fg%2F11cmw_248c!19sChIJvxgVgi1azpQRWEct4hppa4E?authuser=0&hl=pt-BR&rclk=1"
}